dmango/__init__.py
dmango/apps.py
dmango/models.py
dmango/urls.py
dmango/views.py
dmango/static/css/dmango.css
dmango/static/js/dmango.js
dmango/templates/dmango/base.html
dmango-0.2.0.dist-info/DESCRIPTION.rst
dmango-0.2.0.dist-info/METADATA
dmango-0.2.0.dist-info/RECORD
dmango-0.2.0.dist-info/WHEEL
dmango-0.2.0.dist-info/metadata.json
dmango-0.2.0.dist-info/top_level.txt
